mfn/__init__.py
mfn/bootstrap.py
mfn/entropy.py
mfn-0.1.0.dist-info/LICENSE
mfn-0.1.0.dist-info/METADATA
mfn-0.1.0.dist-info/WHEEL
mfn-0.1.0.dist-info/RECORD
