Metadata-Version: 2.1
Name: mfn
Version: 0.1.0
Summary: Implementation in Python of the MFN method to measure complexity & entropy of time series.
Home-page: https://github.com/Martins6/mfn
License: MIT
Author: Adriel Martins
Author-email: am.adriel.martins@gmail.com
Requires-Python: >=3.9,<3.13
Classifier: Development Status :: 3 - Alpha
Classifier: Intended Audience :: Developers
Classifier: License :: OSI Approved :: MIT License
Classifier: Programming Language :: Python :: 3
Classifier: Programming Language :: Python :: 3.9
Classifier: Programming Language :: Python :: 3.10
Classifier: Programming Language :: Python :: 3.11
Classifier: Programming Language :: Python :: 3 :: Only
Classifier: Programming Language :: Python :: 3.12
Classifier: Programming Language :: Python :: 3.8
Requires-Dist: numpy (>=1.26.0,<2.0.0)
Requires-Dist: ordpy (>=1.1.3,<2.0.0)
Project-URL: Paper, https://www.sciencedirect.com/science/article/pii/S0960077923001613
Project-URL: Repository, https://github.com/Martins6/mfn
